{
  "totalConversations": 0,
  "totalRelationsLearned": 1,
  "totalConceptsLearned": 0,
  "lastLearningDate": 1752290299528,
  "qualityScore": 0.5,
  "learningEvents": [
    {
      "timestamp": 1752280602249,
      "type": "user_relations_update",
      "data": {
        "userId": "default",
        "relationsCount": 4
      }
    },
    {
      "timestamp": 1752280882929,
      "type": "user_relations_update",
      "data": {
        "userId": "default",
        "relationsCount": 4
      }
    },
    {
      "timestamp": 1752280882929,
      "type": "user_relations_update",
      "data": {
        "userId": "default",
        "relationsCount": 4
      }
    },
    {
      "timestamp": 1752280882930,
      "type": "user_relations_update",
      "data": {
        "userId": "default",
        "relationsCount": 4
      }
    },
    {
      "timestamp": 1752281161438,
      "type": "user_relations_update",
      "data": {
        "userId": "default",
        "relationsCount": 4
      }
    },
    {
      "timestamp": 1752281161438,
      "type": "user_relations_update",
      "data": {
        "userId": "default",
        "relationsCount": 4
      }
    },
    {
      "timestamp": 1752281161439,
      "type": "user_relations_update",
      "data": {
        "userId": "default",
        "relationsCount": 4
      }
    },
    {
      "timestamp": 1752281442117,
      "type": "user_relations_update",
      "data": {
        "userId": "default",
        "relationsCount": 4
      }
    },
    {
      "timestamp": 1752281442118,
      "type": "user_relations_update",
      "data": {
        "userId": "default",
        "relationsCount": 4
      }
    },
    {
      "timestamp": 1752281442118,
      "type": "user_relations_update",
      "data": {
        "userId": "default",
        "relationsCount": 4
      }
    },
    {
      "timestamp": 1752281722760,
      "type": "user_relations_update",
      "data": {
        "userId": "default",
        "relationsCount": 4
      }
    },
    {
      "timestamp": 1752281722767,
      "type": "user_relations_update",
      "data": {
        "userId": "default",
        "relationsCount": 4
      }
    },
    {
      "timestamp": 1752281722768,
      "type": "user_relations_update",
      "data": {
        "userId": "default",
        "relationsCount": 4
      }
    },
    {
      "timestamp": 1752282003428,
      "type": "user_relations_update",
      "data": {
        "userId": "default",
        "relationsCount": 4
      }
    },
    {
      "timestamp": 1752282003429,
      "type": "user_relations_update",
      "data": {
        "userId": "default",
        "relationsCount": 4
      }
    },
    {
      "timestamp": 1752282003430,
      "type": "user_relations_update",
      "data": {
        "userId": "default",
        "relationsCount": 4
      }
    },
    {
      "timestamp": 1752282281924,
      "type": "user_relations_update",
      "data": {
        "userId": "default",
        "relationsCount": 4
      }
    },
    {
      "timestamp": 1752282281925,
      "type": "user_relations_update",
      "data": {
        "userId": "default",
        "relationsCount": 4
      }
    },
    {
      "timestamp": 1752282281926,
      "type": "user_relations_update",
      "data": {
        "userId": "default",
        "relationsCount": 4
      }
    },
    {
      "timestamp": 1752282562538,
      "type": "user_relations_update",
      "data": {
        "userId": "default",
        "relationsCount": 4
      }
    },
    {
      "timestamp": 1752282562539,
      "type": "user_relations_update",
      "data": {
        "userId": "default",
        "relationsCount": 4
      }
    },
    {
      "timestamp": 1752282562540,
      "type": "user_relations_update",
      "data": {
        "userId": "default",
        "relationsCount": 4
      }
    },
    {
      "timestamp": 1752282843208,
      "type": "user_relations_update",
      "data": {
        "userId": "default",
        "relationsCount": 4
      }
    },
    {
      "timestamp": 1752282843209,
      "type": "user_relations_update",
      "data": {
        "userId": "default",
        "relationsCount": 4
      }
    },
    {
      "timestamp": 1752282843210,
      "type": "user_relations_update",
      "data": {
        "userId": "default",
        "relationsCount": 4
      }
    },
    {
      "timestamp": 1752283123967,
      "type": "user_relations_update",
      "data": {
        "userId": "default",
        "relationsCount": 4
      }
    },
    {
      "timestamp": 1752283123967,
      "type": "user_relations_update",
      "data": {
        "userId": "default",
        "relationsCount": 4
      }
    },
    {
      "timestamp": 1752283123969,
      "type": "user_relations_update",
      "data": {
        "userId": "default",
        "relationsCount": 4
      }
    },
    {
      "timestamp": 1752283405672,
      "type": "user_relations_update",
      "data": {
        "userId": "default",
        "relationsCount": 4
      }
    },
    {
      "timestamp": 1752283405673,
      "type": "user_relations_update",
      "data": {
        "userId": "default",
        "relationsCount": 4
      }
    },
    {
      "timestamp": 1752283405674,
      "type": "user_relations_update",
      "data": {
        "userId": "default",
        "relationsCount": 4
      }
    },
    {
      "timestamp": 1752283699802,
      "type": "user_relations_update",
      "data": {
        "userId": "default",
        "relationsCount": 4
      }
    },
    {
      "timestamp": 1752283699803,
      "type": "user_relations_update",
      "data": {
        "userId": "default",
        "relationsCount": 4
      }
    },
    {
      "timestamp": 1752283699804,
      "type": "user_relations_update",
      "data": {
        "userId": "default",
        "relationsCount": 4
      }
    },
    {
      "timestamp": 1752283999214,
      "type": "user_relations_update",
      "data": {
        "userId": "default",
        "relationsCount": 4
      }
    },
    {
      "timestamp": 1752283999215,
      "type": "user_relations_update",
      "data": {
        "userId": "default",
        "relationsCount": 4
      }
    },
    {
      "timestamp": 1752283999216,
      "type": "user_relations_update",
      "data": {
        "userId": "default",
        "relationsCount": 4
      }
    },
    {
      "timestamp": 1752284299221,
      "type": "user_relations_update",
      "data": {
        "userId": "default",
        "relationsCount": 4
      }
    },
    {
      "timestamp": 1752284299222,
      "type": "user_relations_update",
      "data": {
        "userId": "default",
        "relationsCount": 4
      }
    },
    {
      "timestamp": 1752284299223,
      "type": "user_relations_update",
      "data": {
        "userId": "default",
        "relationsCount": 4
      }
    },
    {
      "timestamp": 1752284599218,
      "type": "user_relations_update",
      "data": {
        "userId": "default",
        "relationsCount": 4
      }
    },
    {
      "timestamp": 1752284599221,
      "type": "user_relations_update",
      "data": {
        "userId": "default",
        "relationsCount": 4
      }
    },
    {
      "timestamp": 1752284599222,
      "type": "user_relations_update",
      "data": {
        "userId": "default",
        "relationsCount": 4
      }
    },
    {
      "timestamp": 1752284899225,
      "type": "user_relations_update",
      "data": {
        "userId": "default",
        "relationsCount": 4
      }
    },
    {
      "timestamp": 1752284899226,
      "type": "user_relations_update",
      "data": {
        "userId": "default",
        "relationsCount": 4
      }
    },
    {
      "timestamp": 1752284899226,
      "type": "user_relations_update",
      "data": {
        "userId": "default",
        "relationsCount": 4
      }
    },
    {
      "timestamp": 1752285199220,
      "type": "user_relations_update",
      "data": {
        "userId": "default",
        "relationsCount": 4
      }
    },
    {
      "timestamp": 1752285199226,
      "type": "user_relations_update",
      "data": {
        "userId": "default",
        "relationsCount": 4
      }
    },
    {
      "timestamp": 1752285199227,
      "type": "user_relations_update",
      "data": {
        "userId": "default",
        "relationsCount": 4
      }
    },
    {
      "timestamp": 1752285499229,
      "type": "user_relations_update",
      "data": {
        "userId": "default",
        "relationsCount": 4
      }
    },
    {
      "timestamp": 1752285499230,
      "type": "user_relations_update",
      "data": {
        "userId": "default",
        "relationsCount": 4
      }
    },
    {
      "timestamp": 1752285499231,
      "type": "user_relations_update",
      "data": {
        "userId": "default",
        "relationsCount": 4
      }
    },
    {
      "timestamp": 1752285799224,
      "type": "user_relations_update",
      "data": {
        "userId": "default",
        "relationsCount": 4
      }
    },
    {
      "timestamp": 1752285799231,
      "type": "user_relations_update",
      "data": {
        "userId": "default",
        "relationsCount": 4
      }
    },
    {
      "timestamp": 1752285799232,
      "type": "user_relations_update",
      "data": {
        "userId": "default",
        "relationsCount": 4
      }
    },
    {
      "timestamp": 1752286099230,
      "type": "user_relations_update",
      "data": {
        "userId": "default",
        "relationsCount": 4
      }
    },
    {
      "timestamp": 1752286099231,
      "type": "user_relations_update",
      "data": {
        "userId": "default",
        "relationsCount": 4
      }
    },
    {
      "timestamp": 1752286099232,
      "type": "user_relations_update",
      "data": {
        "userId": "default",
        "relationsCount": 4
      }
    },
    {
      "timestamp": 1752286399225,
      "type": "user_relations_update",
      "data": {
        "userId": "default",
        "relationsCount": 4
      }
    },
    {
      "timestamp": 1752286399232,
      "type": "user_relations_update",
      "data": {
        "userId": "default",
        "relationsCount": 4
      }
    },
    {
      "timestamp": 1752286399233,
      "type": "user_relations_update",
      "data": {
        "userId": "default",
        "relationsCount": 4
      }
    },
    {
      "timestamp": 1752286699225,
      "type": "user_relations_update",
      "data": {
        "userId": "default",
        "relationsCount": 4
      }
    },
    {
      "timestamp": 1752286699232,
      "type": "user_relations_update",
      "data": {
        "userId": "default",
        "relationsCount": 4
      }
    },
    {
      "timestamp": 1752286699238,
      "type": "user_relations_update",
      "data": {
        "userId": "default",
        "relationsCount": 4
      }
    },
    {
      "timestamp": 1752286999257,
      "type": "user_relations_update",
      "data": {
        "userId": "default",
        "relationsCount": 4
      }
    },
    {
      "timestamp": 1752286999262,
      "type": "user_relations_update",
      "data": {
        "userId": "default",
        "relationsCount": 4
      }
    },
    {
      "timestamp": 1752286999263,
      "type": "user_relations_update",
      "data": {
        "userId": "default",
        "relationsCount": 4
      }
    },
    {
      "timestamp": 1752287299260,
      "type": "user_relations_update",
      "data": {
        "userId": "default",
        "relationsCount": 4
      }
    },
    {
      "timestamp": 1752287299262,
      "type": "user_relations_update",
      "data": {
        "userId": "default",
        "relationsCount": 4
      }
    },
    {
      "timestamp": 1752287299263,
      "type": "user_relations_update",
      "data": {
        "userId": "default",
        "relationsCount": 4
      }
    },
    {
      "timestamp": 1752287599296,
      "type": "user_relations_update",
      "data": {
        "userId": "default",
        "relationsCount": 4
      }
    },
    {
      "timestamp": 1752287599297,
      "type": "user_relations_update",
      "data": {
        "userId": "default",
        "relationsCount": 4
      }
    },
    {
      "timestamp": 1752287599297,
      "type": "user_relations_update",
      "data": {
        "userId": "default",
        "relationsCount": 4
      }
    },
    {
      "timestamp": 1752287899319,
      "type": "user_relations_update",
      "data": {
        "userId": "default",
        "relationsCount": 4
      }
    },
    {
      "timestamp": 1752287899320,
      "type": "user_relations_update",
      "data": {
        "userId": "default",
        "relationsCount": 4
      }
    },
    {
      "timestamp": 1752287899321,
      "type": "user_relations_update",
      "data": {
        "userId": "default",
        "relationsCount": 4
      }
    },
    {
      "timestamp": 1752288199326,
      "type": "user_relations_update",
      "data": {
        "userId": "default",
        "relationsCount": 4
      }
    },
    {
      "timestamp": 1752288199330,
      "type": "user_relations_update",
      "data": {
        "userId": "default",
        "relationsCount": 4
      }
    },
    {
      "timestamp": 1752288199331,
      "type": "user_relations_update",
      "data": {
        "userId": "default",
        "relationsCount": 4
      }
    },
    {
      "timestamp": 1752288499354,
      "type": "user_relations_update",
      "data": {
        "userId": "default",
        "relationsCount": 4
      }
    },
    {
      "timestamp": 1752288499361,
      "type": "user_relations_update",
      "data": {
        "userId": "default",
        "relationsCount": 4
      }
    },
    {
      "timestamp": 1752288499361,
      "type": "user_relations_update",
      "data": {
        "userId": "default",
        "relationsCount": 4
      }
    },
    {
      "timestamp": 1752288799383,
      "type": "user_relations_update",
      "data": {
        "userId": "default",
        "relationsCount": 4
      }
    },
    {
      "timestamp": 1752288799388,
      "type": "user_relations_update",
      "data": {
        "userId": "default",
        "relationsCount": 4
      }
    },
    {
      "timestamp": 1752288799389,
      "type": "user_relations_update",
      "data": {
        "userId": "default",
        "relationsCount": 4
      }
    },
    {
      "timestamp": 1752289099411,
      "type": "user_relations_update",
      "data": {
        "userId": "default",
        "relationsCount": 4
      }
    },
    {
      "timestamp": 1752289099417,
      "type": "user_relations_update",
      "data": {
        "userId": "default",
        "relationsCount": 4
      }
    },
    {
      "timestamp": 1752289099418,
      "type": "user_relations_update",
      "data": {
        "userId": "default",
        "relationsCount": 4
      }
    },
    {
      "timestamp": 1752289399439,
      "type": "user_relations_update",
      "data": {
        "userId": "default",
        "relationsCount": 4
      }
    },
    {
      "timestamp": 1752289399446,
      "type": "user_relations_update",
      "data": {
        "userId": "default",
        "relationsCount": 4
      }
    },
    {
      "timestamp": 1752289399447,
      "type": "user_relations_update",
      "data": {
        "userId": "default",
        "relationsCount": 4
      }
    },
    {
      "timestamp": 1752289699467,
      "type": "user_relations_update",
      "data": {
        "userId": "default",
        "relationsCount": 4
      }
    },
    {
      "timestamp": 1752289699468,
      "type": "user_relations_update",
      "data": {
        "userId": "default",
        "relationsCount": 4
      }
    },
    {
      "timestamp": 1752289699469,
      "type": "user_relations_update",
      "data": {
        "userId": "default",
        "relationsCount": 4
      }
    },
    {
      "timestamp": 1752289999494,
      "type": "user_relations_update",
      "data": {
        "userId": "default",
        "relationsCount": 4
      }
    },
    {
      "timestamp": 1752289999500,
      "type": "user_relations_update",
      "data": {
        "userId": "default",
        "relationsCount": 4
      }
    },
    {
      "timestamp": 1752289999501,
      "type": "user_relations_update",
      "data": {
        "userId": "default",
        "relationsCount": 4
      }
    },
    {
      "timestamp": 1752290299522,
      "type": "user_relations_update",
      "data": {
        "userId": "default",
        "relationsCount": 4
      }
    },
    {
      "timestamp": 1752290299528,
      "type": "user_relations_update",
      "data": {
        "userId": "default",
        "relationsCount": 4
      }
    },
    {
      "timestamp": 1752290299529,
      "type": "user_relations_update",
      "data": {
        "userId": "default",
        "relationsCount": 4
      }
    }
  ]
}